foodlog/__init__.py
foodlog/__main__.py
foodlog/app.py
foodlog/calculator.py
foodlog/logs_browser.py
foodlog/logs_viewer.py
foodlog/menu.py
foodlog/reference_daily_intake.py
foodlog/version.py
foodlog-0.2.1.dist-info/LICENSE
foodlog-0.2.1.dist-info/METADATA
foodlog-0.2.1.dist-info/WHEEL
foodlog-0.2.1.dist-info/entry_points.txt
foodlog-0.2.1.dist-info/top_level.txt
foodlog-0.2.1.dist-info/RECORD
