Metadata-Version: 2.1
Name: foodlog
Version: 0.2.1
Summary: A simple CLI timer to calculate fasting zones.
Home-page: https://github.com/vkostyanetsky/Foodlog
Author: Vlad Kostyanetsky
Author-email: vlad@kostyanetsky.me
License: MIT
Keywords: food diary
Classifier: Development Status :: 5 - Production/Stable
Classifier: Environment :: Console
Classifier: Intended Audience :: End Users/Desktop
Classifier: License :: OSI Approved :: MIT License
Classifier: Operating System :: POSIX
Classifier: Programming Language :: Python :: 3.7
Classifier: Programming Language :: Python :: 3.8
Classifier: Programming Language :: Python :: 3.9
Classifier: Programming Language :: Python :: 3.10
Classifier: Topic :: Utilities
Requires-Python: >=3.7
License-File: LICENSE
Requires-Dist: PyYAML (~=6.0)
Requires-Dist: keyboard (~=0.13.5)
Requires-Dist: vkostyanetsky.cliutils (~=0.2.0)
